pyOptoSigma.py
setup.py
pyOptoSigma.egg-info/PKG-INFO
pyOptoSigma.egg-info/SOURCES.txt
pyOptoSigma.egg-info/dependency_links.txt
pyOptoSigma.egg-info/pbr.json
pyOptoSigma.egg-info/top_level.txt