Metadata-Version: 1.1
Name: pyOptoSigma
Version: 0.1
Summary: Python module for operating stepping moter stages manufactured by OptoSigma and Sigma Koki.
Home-page: https://github.com/ken1row/PyOptoSigma
Author: Kenichiro Tanaka
Author-email: tanaka@am.sanken.osaka-u.ac.jp
License: MIT
Keywords: OptoSigma,Sigma Koki,シグマ光機,translation stages,rotation stages
Platform: UNKNOWN
Classifier: Development Status :: 2 - Pre-Alpha
Classifier: Intended Audience :: Manufacturing
Classifier: Intended Audience :: Science/Research
Classifier: License :: OSI Approved :: MIT License
Classifier: Programming Language :: Python :: 3 :: Only
